{
    "configurations": [
        {
            "name": "Linux",
            "includePath": [
                "${workspaceFolder}/**",
                "/usr/bin/../lib/gcc/x86_64-linux-gnu/7.5.0/../../../../include/c++/7.5.0",
                "/usr/bin/../lib/gcc/x86_64-linux-gnu/7.5.0/../../../../include/x86_64-linux-gnu/c++/7.5.0",
                "/usr/bin/../lib/gcc/x86_64-linux-gnu/7.5.0/../../../../include/c++/7.5.0/backward",
                "/usr/include/clang/6.0.0/include",
                "/usr/local/include",
                "/usr/include/x86_64-linux-gnu",
                "/usr/include"
               
            ],
            "defines": [],
            "compilerPath": "/usr/bin/clang",
            "cStandard": "c11",
            "cppStandard": "c++14",
            "intelliSenseMode": "linux-clang-x64",
            "configurationProvider": "ms-vscode.cmake-tools"
        }
    ],
    "version": 4
}